LICENSE
MANIFEST.in
README.rst
setup.py
setup_qt.py
setup_qt.egg-info/PKG-INFO
setup_qt.egg-info/SOURCES.txt
setup_qt.egg-info/dependency_links.txt
setup_qt.egg-info/requires.txt
setup_qt.egg-info/top_level.txt