Metadata-Version: 1.1
Name: setup-qt
Version: 1.0.0
Summary: Compile Qt resource files, UI files and translations in setup.py
Home-page: https://github.com/xmikos/setup_qt
Author: Michal Krenek (Mikos)
Author-email: m.krenek@gmail.com
License: MIT
Platform: UNKNOWN
Classifier: Development Status :: 5 - Production/Stable
Classifier: Intended Audience :: Developers
Classifier: Framework :: Setuptools Plugin
Classifier: License :: OSI Approved :: MIT License
Classifier: Natural Language :: English
Classifier: Operating System :: OS Independent
Classifier: Programming Language :: Python :: 3
Classifier: Topic :: Software Development :: Libraries :: Python Modules
Classifier: Topic :: Software Development :: Build Tools
Classifier: Topic :: Software Development :: Internationalization
Classifier: Topic :: Software Development :: Localization
Classifier: Topic :: Software Development :: User Interfaces
Classifier: Topic :: System :: Software Distribution
